{
  "running": true,
  "lastCheck": "2026-01-31T07:34:17.336Z",
  "healingActions": [
    {
      "timestamp": "2026-01-31T07:22:37.767Z",
      "file": "d0t-signals.json",
      "crawler": "d0t-signals.js",
      "success": true
    },
    {
      "timestamp": "2026-01-31T07:22:39.866Z",
      "file": "polymarket.json",
      "crawler": "polymarket-crawler.js",
      "success": true
    },
    {
      "timestamp": "2026-01-31T07:22:46.179Z",
      "file": "x-conversations.json",
      "crawler": "x-conversation-crawler.js",
      "success": true
    },
    {
      "timestamp": "2026-01-31T07:23:02.239Z",
      "file": "library-sync.json",
      "crawler": "library-sync-crawler.js",
      "success": true
    },
    {
      "timestamp": "2026-01-31T07:23:34.335Z",
      "file": "polymarket.json",
      "crawler": "polymarket-crawler.js",
      "success": true
    },
    {
      "timestamp": "2026-01-31T07:23:50.206Z",
      "file": "library-sync.json",
      "crawler": "library-sync-crawler.js",
      "success": true
    },
    {
      "timestamp": "2026-01-31T07:24:22.303Z",
      "file": "polymarket.json",
      "crawler": "polymarket-crawler.js",
      "success": true
    },
    {
      "timestamp": "2026-01-31T07:24:38.027Z",
      "file": "library-sync.json",
      "crawler": "library-sync-crawler.js",
      "success": true
    },
    {
      "timestamp": "2026-01-31T07:25:10.923Z",
      "file": "d0t-signals.json",
      "crawler": "d0t-signals.js",
      "success": true
    },
    {
      "timestamp": "2026-01-31T07:25:13.013Z",
      "file": "polymarket.json",
      "crawler": "polymarket-crawler.js",
      "success": true
    },
    {
      "timestamp": "2026-01-31T07:25:28.803Z",
      "file": "library-sync.json",
      "crawler": "library-sync-crawler.js",
      "success": true
    },
    {
      "timestamp": "2026-01-31T07:26:00.897Z",
      "file": "polymarket.json",
      "crawler": "polymarket-crawler.js",
      "success": true
    },
    {
      "timestamp": "2026-01-31T07:26:16.935Z",
      "file": "library-sync.json",
      "crawler": "library-sync-crawler.js",
      "success": true
    },
    {
      "timestamp": "2026-01-31T07:26:49.024Z",
      "file": "polymarket.json",
      "crawler": "polymarket-crawler.js",
      "success": true
    },
    {
      "timestamp": "2026-01-31T07:27:05.999Z",
      "file": "library-sync.json",
      "crawler": "library-sync-crawler.js",
      "success": true
    },
    {
      "timestamp": "2026-01-31T07:27:39.268Z",
      "file": "d0t-signals.json",
      "crawler": "d0t-signals.js",
      "success": true
    },
    {
      "timestamp": "2026-01-31T07:27:41.363Z",
      "file": "polymarket.json",
      "crawler": "polymarket-crawler.js",
      "success": true
    },
    {
      "timestamp": "2026-01-31T07:27:57.273Z",
      "file": "library-sync.json",
      "crawler": "library-sync-crawler.js",
      "success": true
    },
    {
      "timestamp": "2026-01-31T07:28:29.363Z",
      "file": "polymarket.json",
      "crawler": "polymarket-crawler.js",
      "success": true
    },
    {
      "timestamp": "2026-01-31T07:28:35.688Z",
      "file": "x-conversations.json",
      "crawler": "x-conversation-crawler.js",
      "success": true
    },
    {
      "timestamp": "2026-01-31T07:28:51.778Z",
      "file": "library-sync.json",
      "crawler": "library-sync-crawler.js",
      "success": true
    },
    {
      "timestamp": "2026-01-31T07:29:23.880Z",
      "file": "polymarket.json",
      "crawler": "polymarket-crawler.js",
      "success": true
    },
    {
      "timestamp": "2026-01-31T07:29:39.594Z",
      "file": "library-sync.json",
      "crawler": "library-sync-crawler.js",
      "success": true
    },
    {
      "timestamp": "2026-01-31T07:30:12.508Z",
      "file": "d0t-signals.json",
      "crawler": "d0t-signals.js",
      "success": true
    },
    {
      "timestamp": "2026-01-31T07:30:14.594Z",
      "file": "polymarket.json",
      "crawler": "polymarket-crawler.js",
      "success": true
    },
    {
      "timestamp": "2026-01-31T07:30:30.354Z",
      "file": "library-sync.json",
      "crawler": "library-sync-crawler.js",
      "success": true
    },
    {
      "timestamp": "2026-01-31T07:31:02.446Z",
      "file": "polymarket.json",
      "crawler": "polymarket-crawler.js",
      "success": true
    },
    {
      "timestamp": "2026-01-31T07:31:18.183Z",
      "file": "library-sync.json",
      "crawler": "library-sync-crawler.js",
      "success": true
    },
    {
      "timestamp": "2026-01-31T07:31:50.282Z",
      "file": "polymarket.json",
      "crawler": "polymarket-crawler.js",
      "success": true
    },
    {
      "timestamp": "2026-01-31T07:32:06.274Z",
      "file": "library-sync.json",
      "crawler": "library-sync-crawler.js",
      "success": true
    },
    {
      "timestamp": "2026-01-31T07:32:39.608Z",
      "file": "d0t-signals.json",
      "crawler": "d0t-signals.js",
      "success": true
    },
    {
      "timestamp": "2026-01-31T07:32:41.701Z",
      "file": "polymarket.json",
      "crawler": "polymarket-crawler.js",
      "success": true
    },
    {
      "timestamp": "2026-01-31T07:32:57.458Z",
      "file": "library-sync.json",
      "crawler": "library-sync-crawler.js",
      "success": true
    },
    {
      "timestamp": "2026-01-31T07:33:29.561Z",
      "file": "polymarket.json",
      "crawler": "polymarket-crawler.js",
      "success": true
    },
    {
      "timestamp": "2026-01-31T07:33:45.319Z",
      "file": "library-sync.json",
      "crawler": "library-sync-crawler.js",
      "success": true
    },
    {
      "timestamp": "2026-01-31T07:34:17.415Z",
      "file": "polymarket.json",
      "crawler": "polymarket-crawler.js",
      "success": true
    },
    {
      "timestamp": "2026-01-31T07:34:23.765Z",
      "file": "x-conversations.json",
      "crawler": "x-conversation-crawler.js",
      "success": true
    },
    {
      "timestamp": "2026-01-31T07:34:39.928Z",
      "file": "library-sync.json",
      "crawler": "library-sync-crawler.js",
      "success": true
    }
  ],
  "crawlerProcesses": [],
  "stats": {
    "checks": 15,
    "heals": 38,
    "failures": 0
  }
}